envo/__init__.py
envo/__main__.py
envo/comp.py
envo/const.py
envo/devops.py
envo/e2e.py
envo/env.py
envo/environ.py
envo/exceptions.py
envo/logs.py
envo/scripts.py
envo/shell.py
envo/status.py
envo/styles.py
envo/templates/comm_env.py.templ
envo/templates/env.py.templ
envo/utils.py
envo/vendored/__init__.py
envo/vendored/colorizer.py
envo/venv_utils.py
envo-1.5.5.dist-info/METADATA
envo-1.5.5.dist-info/WHEEL
envo-1.5.5.dist-info/entry_points.txt
envo-1.5.5.dist-info/RECORD
