Metadata-Version: 2.1
Name: envo
Version: 1.5.5
Summary: Smart Environments handling - Define command hooks, file hooks and env variables in python and activate hot reloaded shells.
License: Apache 2.0
Author: Damian Krystkiewicz
Author-email: damian.krystkiewicz@gmail.com
Requires-Python: >=3.8,<4.0
Classifier: Development Status :: 5 - Production/Stable
Classifier: Environment :: Console
Classifier: Intended Audience :: Developers
Classifier: License :: Other/Proprietary License
Classifier: Operating System :: POSIX :: Linux
Classifier: Programming Language :: Python :: 3
Classifier: Programming Language :: Python :: 3.8
Classifier: Programming Language :: Python :: 3.9
Classifier: Programming Language :: Python :: 3.10
Classifier: Programming Language :: Python :: 3.11
Classifier: Programming Language :: Python :: 3.12
Classifier: Programming Language :: Python :: 3.13
Classifier: Programming Language :: Python :: 3.7
Classifier: Topic :: Software Development :: Libraries :: Python Modules
Classifier: Topic :: System :: Shells
Requires-Dist: envium (>=1.1.1,<2.0.0)
Requires-Dist: prompt_toolkit (==3.0.26)
Requires-Dist: pygments (>=2,<3)
Requires-Dist: rhei (>=0,<1)
Requires-Dist: rich
Requires-Dist: xonsh (==0.13.1)
Project-URL: homepage, https://gitlab.com/plasma-opensource/envo
